QianruQianchuJavaWeb/README.md
QianruQianchuJavaWeb/__init__.py
QianruQianchuJavaWeb/__main__.py
QianruQianchuJavaWeb/file.epub
QianruQianchuJavaWeb/index.html
QianruQianchuJavaWeb/css/__init__.py
QianruQianchuJavaWeb/css/annotations.css
QianruQianchuJavaWeb/css/main.css
QianruQianchuJavaWeb/css/normalize.css
QianruQianchuJavaWeb/css/popup.css
QianruQianchuJavaWeb/font/__init__.py
QianruQianchuJavaWeb/font/fontello.eot
QianruQianchuJavaWeb/font/fontello.svg
QianruQianchuJavaWeb/font/fontello.ttf
QianruQianchuJavaWeb/font/fontello.woff
QianruQianchuJavaWeb/img/__init__.py
QianruQianchuJavaWeb/img/annotator-glyph-sprite.png
QianruQianchuJavaWeb/img/annotator-icon-sprite.png
QianruQianchuJavaWeb/img/apple-touch-icon.png
QianruQianchuJavaWeb/img/cancelfullscreen.png
QianruQianchuJavaWeb/img/close.png
QianruQianchuJavaWeb/img/fullscreen.png
QianruQianchuJavaWeb/img/loader.gif
QianruQianchuJavaWeb/img/menu-icon.png
QianruQianchuJavaWeb/img/save.png
QianruQianchuJavaWeb/img/saved.png
QianruQianchuJavaWeb/img/settings-s.png
QianruQianchuJavaWeb/img/settings.png
QianruQianchuJavaWeb/img/star.png
QianruQianchuJavaWeb/js/__init__.py
QianruQianchuJavaWeb/js/epub.js
QianruQianchuJavaWeb/js/epub.min.js
QianruQianchuJavaWeb/js/epub.min.map
QianruQianchuJavaWeb/js/hooks.min.js
QianruQianchuJavaWeb/js/hooks.min.map
QianruQianchuJavaWeb/js/reader.js
QianruQianchuJavaWeb/js/reader.js.map
QianruQianchuJavaWeb/js/reader.min.js
QianruQianchuJavaWeb/js/reader.min.map
QianruQianchuJavaWeb/js/hooks/__init__.py
QianruQianchuJavaWeb/js/hooks/extensions/__init__.py
QianruQianchuJavaWeb/js/hooks/extensions/highlight.js
QianruQianchuJavaWeb/js/libs/__init__.py
QianruQianchuJavaWeb/js/libs/jquery.min.js
QianruQianchuJavaWeb/js/libs/localforage.min.js
QianruQianchuJavaWeb/js/libs/screenfull.js
QianruQianchuJavaWeb/js/libs/screenfull.min.js
QianruQianchuJavaWeb/js/libs/zip.min.js
QianruQianchuJavaWeb/js/plugins/__init__.py
QianruQianchuJavaWeb/js/plugins/hypothesis.js
qianru_qianchu_java_web-2024.3.1.0.dist-info/METADATA
qianru_qianchu_java_web-2024.3.1.0.dist-info/WHEEL
qianru_qianchu_java_web-2024.3.1.0.dist-info/entry_points.txt
qianru_qianchu_java_web-2024.3.1.0.dist-info/top_level.txt
qianru_qianchu_java_web-2024.3.1.0.dist-info/RECORD
